qq/__init__.py
qq/__main__.py
qq/abc.py
qq/asset.py
qq/audio.py
qq/backoff.py
qq/channel.py
qq/client.py
qq/colour.py
qq/embeds.py
qq/emoji.py
qq/enum.py
qq/error.py
qq/file.py
qq/flags.py
qq/gateway.py
qq/guild.py
qq/http.py
qq/iterators.py
qq/member.py
qq/mention.py
qq/message.py
qq/mixins.py
qq/nest_asyncio.py
qq/object.py
qq/partial_emoji.py
qq/permissions.py
qq/raw_models.py
qq/reaction.py
qq/role.py
qq/shard.py
qq/state.py
qq/user.py
qq/utils.py
qq/ext/commands/__init__.py
qq/ext/commands/_types.py
qq/ext/commands/bot.py
qq/ext/commands/cog.py
qq/ext/commands/context.py
qq/ext/commands/converter.py
qq/ext/commands/cooldowns.py
qq/ext/commands/core.py
qq/ext/commands/errors.py
qq/ext/commands/flags.py
qq/ext/commands/help.py
qq/ext/commands/view.py
qq/ext/tasks/__init__.py
qq/types/audio.py
qq/types/channel.py
qq/types/embed.py
qq/types/emoji.py
qq/types/guild.py
qq/types/member.py
qq/types/message.py
qq/types/raw_models.py
qq/types/role.py
qq/types/user.py
qq.py-1.1.2.dist-info/LICENSE
qq.py-1.1.2.dist-info/METADATA
qq.py-1.1.2.dist-info/WHEEL
qq.py-1.1.2.dist-info/top_level.txt
qq.py-1.1.2.dist-info/RECORD
