Metadata-Version: 2.1
Name: qq.py
Version: 1.1.2
Summary: QQ 频道 API 的 Python Wrapper
Home-page: https://github.com/foxwhite25/qq.py
Author: foxwhite25
Author-email: vct.xie@gmail.com
License: MIT
Platform: UNKNOWN
Classifier: Development Status :: 4 - Beta
Classifier: License :: OSI Approved :: MIT License
Classifier: Intended Audience :: Developers
Classifier: Natural Language :: English
Classifier: Natural Language :: Chinese (Simplified)
Classifier: Operating System :: OS Independent
Classifier: Programming Language :: Python :: 3.8
Classifier: Programming Language :: Python :: 3.9
Classifier: Programming Language :: Python :: 3.10
Classifier: Framework :: AsyncIO
Classifier: Framework :: aiohttp
Classifier: Topic :: Internet
Classifier: Topic :: Software Development :: Libraries
Classifier: Topic :: Software Development :: Libraries :: Python Modules
Classifier: Topic :: Utilities
Classifier: Typing :: Typed
Requires-Python: >=3.8.0
License-File: LICENSE
Requires-Dist: aiohttp (<=4.0.0,>=3.6.0)
Provides-Extra: docs
Requires-Dist: sphinx (==4.0.2) ; extra == 'docs'
Requires-Dist: sphinxcontrib-trio (==1.1.2) ; extra == 'docs'
Requires-Dist: sphinxcontrib-websupport ; extra == 'docs'
